MANIFEST.in
README.txt
setup.cfg
setup.py
docs/HISTORY.txt
docs/INSTALL.txt
docs/LICENSE.GPL
docs/LICENSE.txt
docs/Makefile
docs/conf.py
docs/index.txt
docs/make.bat
docs/resources/keywordold.png
docs/resources/keywordportlet.png
docs/resources/keywordtree.png
redomino/__init__.py
redomino.advancedkeyword.egg-info/PKG-INFO
redomino.advancedkeyword.egg-info/SOURCES.txt
redomino.advancedkeyword.egg-info/dependency_links.txt
redomino.advancedkeyword.egg-info/entry_points.txt
redomino.advancedkeyword.egg-info/namespace_packages.txt
redomino.advancedkeyword.egg-info/not-zip-safe
redomino.advancedkeyword.egg-info/requires.txt
redomino.advancedkeyword.egg-info/top_level.txt
redomino/advancedkeyword/TODO.txt
redomino/advancedkeyword/__init__.py
redomino/advancedkeyword/config.py
redomino/advancedkeyword/configure.zcml
redomino/advancedkeyword/i18n.sh
redomino/advancedkeyword/indexers.py
redomino/advancedkeyword/vocabularies.py
redomino/advancedkeyword/browser/__init__.py
redomino/advancedkeyword/browser/configure.zcml
redomino/advancedkeyword/browser/interfaces.py
redomino/advancedkeyword/browser/keywordmapcontrolpanel.py
redomino/advancedkeyword/browser/keywords.py
redomino/advancedkeyword/browser/utils.py
redomino/advancedkeyword/browser/viewlets.py
redomino/advancedkeyword/browser/jbot/Products.Archetypes.skins.archetypes.widgets.keyword.pt
redomino/advancedkeyword/browser/resources/collapsed.png
redomino/advancedkeyword/browser/resources/expanded.png
redomino/advancedkeyword/browser/resources/jquery.keywordtree.css
redomino/advancedkeyword/browser/resources/jquery.keywordtree.js
redomino/advancedkeyword/browser/resources/jquery.shiftcheckbox.js
redomino/advancedkeyword/browser/resources/subjectkeywordtree.js
redomino/advancedkeyword/browser/resources/test/jquery-1.4.4.min.js
redomino/advancedkeyword/browser/resources/test/qunit.css
redomino/advancedkeyword/browser/resources/test/qunit.js
redomino/advancedkeyword/browser/resources/test/test.html
redomino/advancedkeyword/browser/resources/test/test.js
redomino/advancedkeyword/browser/templates/advancedkeywords.options.js.pt
redomino/advancedkeyword/browser/templates/keywordmap.pt
redomino/advancedkeyword/browser/templates/keywords_viewlet.pt
redomino/advancedkeyword/browser/templates/macros.pt
redomino/advancedkeyword/locales/redomino.advancedkeyword-manual.pot
