Metadata-Version: 1.0
Name: redomino.advancedkeyword
Version: 1.4
Summary: Redomino Advanced Keyword Management
Home-page: https://github.com/redomino/redomino.advancedkeyword
Author: Davide Moro
Author-email: davide.moro@redomino.com
License: GPL
Platform: UNKNOWN
Classifier: Framework :: Plone
Classifier: Programming Language :: Python
